setup.py
speedyspotify/__init__.py
speedyspotify/client.py
speedyspotify/oauth2.py
speedyspotify/util.py
speedyspotify.egg-info/PKG-INFO
speedyspotify.egg-info/SOURCES.txt
speedyspotify.egg-info/dependency_links.txt
speedyspotify.egg-info/requires.txt
speedyspotify.egg-info/top_level.txt