Metadata-Version: 1.0
Name: speedyspotify
Version: 0.2.0
Summary: Async Spotify web API client
Home-page: https://github.com/steinitzu/speedyspotify
Author: Steinthor Palsson
Author-email: steini90@gmail.com
License: LICENSE
Platform: UNKNOWN
